language_renderer7/__init__.py
language_renderer7/core.py
language_renderer7-0.1.0.dist-info/licenses/LICENSE
language_renderer7-0.1.0.dist-info/METADATA
language_renderer7-0.1.0.dist-info/WHEEL
language_renderer7-0.1.0.dist-info/top_level.txt
language_renderer7-0.1.0.dist-info/RECORD
