Metadata-Version: 2.4
Name: language-renderer7
Version: 0.1.0
Summary: A multi-language to Python code renderer with CLI visualization.
Home-page: https://pypi.org/project/language-renderer7/
Author: Adam Alcander et Eden
Author-email: Adam Alcander et Eden <aeden6877@gmail.com>
License: MIT
Project-URL: Homepage, https://pypi.org/project/language-renderer7/
Project-URL: Source, https://github.com/EdenGithhub/LanguageRenderer7
Project-URL: Tracker, https://github.com/EdenGithhub/LanguageRenderer7/issues
Requires-Python: >=3.7
License-File: LICENSE
Requires-Dist: matplotlib
Requires-Dist: numpy
Requires-Dist: colorama
Requires-Dist: rich
Requires-Dist: pygments
Requires-Dist: beautifulsoup4
Requires-Dist: requests
Requires-Dist: tqdm
Requires-Dist: lxml
Requires-Dist: networkx
Dynamic: license-file
